{
  "name": "hbvAnc731Base",
  "version": "1.0",
  "tag": "",
  "description": "",
  "uses": [],
  "sources": [
    {
      "table": "amrs.obs",
      "alias": "o"
    },
    {
      "table": "etl.flat_patient_identifiers_v1",
      "alias": "flat_identifiers",
      "join": {
        "type": "LEFT",
        "joinCondition": "o.person_id = flat_identifiers.patient_id"
      }
    }
  ],
  "columns": [
    {
      "type": "simple_column",
      "alias": "person_id",
      "column": "o.person_id"
    },
    {
      "type": "simple_column",
      "alias": "ccc_number",
      "column": "flat_identifiers.ccc"
    },
    {
      "type": "simple_column",
      "alias": "upi_number",
      "column": "flat_identifiers.nupi"
    },
    {
      "type": "derived_column",
      "alias": "hbv_screened_positive_anc",
      "expressionType": "simple_expression",
      "expressionOptions": {
        "expression": "if(value_coded = 1065, 1, NULL)"
      }
    }
  ],
  "filters": {
    "conditionJoinOperator": "and",
    "conditions": [
      {
        "filterType": "tableColumns",
        "conditionExpression": "o.concept_id in (12447)",
        "parameterName": ""
      },
      {
        "filterType": "tableColumns",
        "conditionExpression": "o.obs_datetime >= ?",
        "parameterName": "startDate"
      },
      {
        "filterType": "tableColumns",
        "conditionExpression": "o.obs_datetime <= ?",
        "parameterName": "endDate"
      },
      {
        "filterType": "tableColumns",
        "conditionExpression": "o.location_id in ?",
        "parameterName": "locations"
      }
    ]
  },
  "groupBy": {
    "groupParam": "groupByParam",
    "columns": ["o.person_id"],
    "excludeParam": "excludeParam"
  }
}
